flogg/__init__.py
flogg/flogg.py
flogg-1.0.1.dist-info/LICENSE
flogg-1.0.1.dist-info/METADATA
flogg-1.0.1.dist-info/WHEEL
flogg-1.0.1.dist-info/top_level.txt
flogg-1.0.1.dist-info/RECORD
