Metadata-Version: 2.1
Name: flogg
Version: 1.0.1
Summary: Improved logging system for Python
Home-page: https://github.com/DovaX/flog
Author: DovaX
Author-email: dovax.ai@gmail.com
Classifier: Programming Language :: Python :: 3
Classifier: License :: OSI Approved :: MIT License
Classifier: Operating System :: OS Independent
Requires-Python: >=3.6
License-File: LICENSE
